pdnd_client/__init__.py
pdnd_client/client.py
pdnd_client/config.py
pdnd_client/jwt_generator.py
pdnd_python_client-0.1.15.dist-info/licenses/LICENSE
pdnd_python_client-0.1.15.dist-info/METADATA
pdnd_python_client-0.1.15.dist-info/WHEEL
pdnd_python_client-0.1.15.dist-info/top_level.txt
pdnd_python_client-0.1.15.dist-info/RECORD
