Metadata-Version: 2.4
Name: pdnd-python-client
Version: 0.1.15
Summary: Client Python per autenticazione e interazione con le API della Piattaforma Digitale Nazionale Dati (PDND).
Author-email: Francesco Loreti <francesco.loreti@isprambiente.it>
License-Expression: MIT
Project-URL: Homepage, https://github.com/isprambiente/pdnd-python-client
Project-URL: Issues, https://github.com/isprambiente/pdnd-python-client/issues
Classifier: Programming Language :: Python :: 3
Classifier: Programming Language :: Python :: 3.12
Classifier: Operating System :: OS Independent
Requires-Python: >=3.12
License-File: LICENSE
Requires-Dist: PyJWT>=2.0.0
Requires-Dist: cryptography
Requires-Dist: requests
Provides-Extra: dev
Requires-Dist: pytest; extra == "dev"
Requires-Dist: pytest-watch; extra == "dev"
Requires-Dist: requests-mock; extra == "dev"
Dynamic: license-file
